<?xml version="1.0" encoding="utf-8"?>
<list>
  <question>
    <id>1</id>
    <image>'1'</image>
    <questionName>'Крымскотатарское название селения Перевальное'</questionName>
    <answerChoice>
      <list>
        <item>'Ангъара'</item>
        <item>'Ана-Эли'</item>
        <item>'Бешуй'</item>
        <item>'Бавурчы'</item>
      </list>
    </answerChoice>
    <correctAnswer>'Ангъара'</correctAnswer>
  </question>
  <question>
    <id>2</id>
    <image>'1'</image>
    <questionName>'Историческое название селения Каменка'</questionName>
    <answerChoice>
      <list>
        <item>'Ангъара'</item>
        <item>'Ана-Эли'</item>
        <item>'Бешуй'</item>
        <item>'Бавурчы'</item>
      </list>
    </answerChoice>
    <correctAnswer>'Бавурчы'</correctAnswer>
  </question>
  <question>
    <id>3</id>
    <image>'1'</image>
    <questionName>'Поселение в Юго-Западном Крыму, в новое время — упразднённое впоследствии село Подгородное, ныне исторический район в западной части города Бахчисарая'</questionName>
    <answerChoice>
      <list>
        <item>'Эски-Кермен'</item>
        <item>'Эски-Юрт'</item>
        <item>'Эски-Сарай'</item>
        <item>'Ени-Кале'</item>
      </list>
    </answerChoice>
    <correctAnswer>'Эски-Юрт'</correctAnswer>
  </question>
  <question>
    <id>4</id>
    <image>'1'</image>
    <questionName>'Наиболее представительный памятник Золотой орды в Крыму
'</questionName>
    <answerChoice>
      <list>
        <item>'Бахчисарайский Ханский дворец'</item>
        <item>'Мечеть Бейбарса в Старом Крыму'</item>
        <item>'Мечеть Узбек-Хана в Старом Крыму'</item>
        <item>'Ханский дворец Девлет-Сарай возле Бахчисарая'</item>
      </list>
    </answerChoice>
    <correctAnswer>'Мечеть Узбек-Хана в Старом Крыму'</correctAnswer>
  </question>
  <question>
    <id>5</id>
    <image>'1'</image>
    <questionName>'Крымскотатарское название города Симферополь'</questionName>
    <answerChoice>
      <list>
        <item>'Кефе'</item>
        <item>'Акъмесджит'</item>
        <item>'Кезлев'</item>
        <item>'Акъ-Мечеть'</item>
      </list>
    </answerChoice>
    <correctAnswer>'Акъмесджит'</correctAnswer>
  </question>
  <question>
    <id>6</id>
    <image>'1'</image>
    <questionName>'Где находится крепость Еникале, изображенная на фотографии?'</questionName>
    <answerChoice>
      <list>
        <item>'В Керчи'</item>
        <item>'В Бахчисарае'</item>
        <item>'В Судаке'</item>
        <item>'В Севастополе'</item>
      </list>
    </answerChoice>
    <correctAnswer>'В Керчи'</correctAnswer>
  </question>
  <question>
    <id>7</id>
    <image>'1'</image>
    <questionName>'Крымскотатарское название селения Пионерское'</questionName>
    <answerChoice>
      <list>
        <item>'Къарача-Къанъгъыл'</item>
        <item>'Ангъара'</item>
        <item>'Ана-Эли'</item>
        <item>'Джолман'</item>
      </list>
    </answerChoice>
    <correctAnswer>'Джолман'</correctAnswer>
  </question>
  <question>
    <id>8</id>
    <image>'1'</image>
    <questionName>'Какое озеро изображено на карте?'</questionName>
    <answerChoice>
      <list>
        <item>'Сасык'</item>
        <item>'Джарылгач'</item>
        <item>'Лиман'</item>
        <item>'Текерлы'</item>
      </list>
    </answerChoice>
    <correctAnswer>'Сасык'</correctAnswer>
  </question>
  <question>
    <id>9</id>
    <image>'1'</image>
    <questionName>'Где находится мечеть изображенная на фото?'</questionName>
    <answerChoice>
      <list>
        <item>'В Бахчисарае'</item>
        <item>'В Кезлеве'</item>
        <item>'В Старом Крыму'</item>
        <item>'В Ялте'</item>
      </list>
    </answerChoice>
    <correctAnswer>'В Старом Крыму'</correctAnswer>
  </question>
  <question>
    <id>10</id>
    <image>'1'</image>
    <questionName>'Самая длинная река полуострова'</questionName>
    <answerChoice>
      <list>
        <item>'Альма'</item>
        <item>'Салгир'</item>
        <item>'Ангара'</item>
        <item>'Чюрюк-Су'</item>
      </list>
    </answerChoice>
    <correctAnswer>'Салгир'</correctAnswer>
  </question>
  <question>
    <id>11</id>
    <image>'1'</image>
    <questionName>'Крымскотатарское название селения Доброе'</questionName>
    <answerChoice>
      <list>
        <item>'Къарача-Къанъгъыл'</item>
        <item>'Ангъара'</item>
        <item>'Ана-Эли'</item>
        <item>'Мамут-Султан'</item>
      </list>
    </answerChoice>
    <correctAnswer>'Мамут-Султан'</correctAnswer>
  </question>
  <question>
    <id>12</id>
    <image>'1'</image>
    <questionName>'Историческое название города Керчь'</questionName>
    <answerChoice>
      <list>
        <item>'Керич'</item>
        <item>'Боспорос'</item>
        <item>'Черкио'</item>
        <item>'Пантикапайон'</item>
      </list>
    </answerChoice>
    <correctAnswer>'Керич'</correctAnswer>
  </question>
  <question>
    <id>13</id>
    <image>'1'</image>
    <questionName>'Самая большая пещера в Крыму'</questionName>
    <answerChoice>
      <list>
        <item>'Киик-коба'</item>
        <item>'Кызыл-коба'</item>
        <item>'Шан-коба'</item>
        <item>'Шайтан-коба'</item>
      </list>
    </answerChoice>
    <correctAnswer>'Кызыл-коба'</correctAnswer>
  </question>
  <question>
    <id>14</id>
    <image>'1'</image>
    <questionName>'Крымскотатарское название селения Укромное'</questionName>
    <answerChoice>
      <list>
        <item>'Къарача-Къанъгъыл'</item>
        <item>'Ангъара'</item>
        <item>'Янъы Сарабуз'</item>
        <item>'Мамут-Султан'</item>
      </list>
    </answerChoice>
    <correctAnswer>'Янъы Сарабуз'</correctAnswer>
  </question>
  <question>
    <id>15</id>
    <image>'1'</image>
    <questionName>'Красные пещеры так же известны под названием'</questionName>
    <answerChoice>
      <list>
        <item>'Киик-коба'</item>
        <item>'Кызыл-коба'</item>
        <item>'Шан-коба'</item>
        <item>'Шайтан-коба'</item>
      </list>
    </answerChoice>
    <correctAnswer>'Кызыл-коба'</correctAnswer>
  </question>
  <question>
    <id>16</id>
    <image>'1'</image>
    <questionName>'Крымскотатарское название селения Партизанское'</questionName>
    <answerChoice>
      <list>
        <item>'Къарача-Къанъгъыл'</item>
        <item>'Саблы'</item>
        <item>'Янъы Сарабуз'</item>
        <item>'Мамут-Султан'</item>
      </list>
    </answerChoice>
    <correctAnswer>'Саблы'</correctAnswer>
  </question>
  <question>
    <id>17</id>
    <image>'1'</image>
    <questionName>'Историческое название селения Морское'</questionName>
    <answerChoice>
      <list>
        <item>'Къапсихор'</item>
        <item>'Янъы Сарабуз'</item>
        <item>'Мамут-Султан'</item>
        <item>'Къарача-Къанъгъыл'</item>
      </list>
    </answerChoice>
    <correctAnswer>'Къапсихор'</correctAnswer>
  </question>
  <question>
    <id>18</id>
    <image>'1'</image>
    <questionName>'Старое название города Старый Крым
'</questionName>
    <answerChoice>
      <list>
        <item>'Кезлев'</item>
        <item>'Солхат'</item>
        <item>'Акъмесджит'</item>
        <item>'Кефе'</item>
      </list>
    </answerChoice>
    <correctAnswer>'Солхат'</correctAnswer>
  </question>
  <question>
    <id>19</id>
    <image>'1'</image>
    <questionName>'Крымскотатарское название города Феодосия'</questionName>
    <answerChoice>
      <list>
        <item>'Кезлев'</item>
        <item>'Эски Къырым'</item>
        <item>'Акъмесджит'</item>
        <item>'Кефе'</item>
      </list>
    </answerChoice>
    <correctAnswer>'Кефе'</correctAnswer>
  </question>
  <question>
    <id>20</id>
    <image>'1'</image>
    <questionName>'Древнее поселение у подножия Чуфут-Кале и первая столица Крымского ханства'</questionName>
    <answerChoice>
      <list>
        <item>'Бахчисарай'</item>
        <item>'Салачыкъ'</item>
        <item>'Аджы-Болат'</item>
        <item>'Акъшейх'</item>
      </list>
    </answerChoice>
    <correctAnswer>'Салачыкъ'</correctAnswer>
  </question>
  <question>
    <id>21</id>
    <image>'1'</image>
    <questionName>'Крымскотатарское название селения Лозовое'</questionName>
    <answerChoice>
      <list>
        <item>'Къапсихор'</item>
        <item>'Янъы Сарабуз'</item>
        <item>'Мамут-Султан'</item>
        <item>'Эски-Орда'</item>
      </list>
    </answerChoice>
    <correctAnswer>'Эски-Орда'</correctAnswer>
  </question>
  <question>
    <id>22</id>
    <image>'1'</image>
    <questionName>'«Симферополь» в переводе с греческого'</questionName>
    <answerChoice>
      <list>
        <item>'«город-собиратель» '</item>
        <item>'«город славы»'</item>
        <item>'«богатый город»'</item>
        <item>'«город греков»'</item>
      </list>
    </answerChoice>
    <correctAnswer>'«город-собиратель» '</correctAnswer>
  </question>
  <question>
    <id>23</id>
    <image>'1'</image>
    <questionName>'Историческое название деревни, в которой с 1806 года компактно проживала колония немецких эмигрантов (ныне село в Белогорском районе)'</questionName>
    <answerChoice>
      <list>
        <item>'Вюртемберг'</item>
        <item>'Фриденталь'</item>
        <item>'Розенталь'</item>
        <item>'Нейзац'</item>
      </list>
    </answerChoice>
    <correctAnswer>'Фриденталь'</correctAnswer>
  </question>
  <question>
    <id>24</id>
    <image>'1'</image>
    <questionName>'Крымскотатарское название селения Угловое'</questionName>
    <answerChoice>
      <list>
        <item>'Къапсихор'</item>
        <item>'Аджы Болат'</item>
        <item>'Мамут-Султан'</item>
        <item>'Эски-Орда'</item>
      </list>
    </answerChoice>
    <correctAnswer>'Аджы Болат'</correctAnswer>
  </question>
  <question>
    <id>25</id>
    <image>'1'</image>
    <questionName>'Наивысшая точка протянувшейся вдоль Южного берега Крыма Главной гряды — это гора'</questionName>
    <answerChoice>
      <list>
        <item>'Чатыр-Дагъ'</item>
        <item>'Сапун дагъы'</item>
        <item>'Роман-Кош'</item>
        <item>'Къара-Дагъ'</item>
      </list>
    </answerChoice>
    <correctAnswer>'Роман-Кош'</correctAnswer>
  </question>
  <question>
    <id>26</id>
    <image>'1'</image>
    <questionName>'Самый высокий водопад Крыма'</questionName>
    <answerChoice>
      <list>
        <item>'Су-Учхан'</item>
        <item>'Джурла'</item>
        <item>'Джур-Джур'</item>
        <item>'Учан-Су'</item>
      </list>
    </answerChoice>
    <correctAnswer>'Учан-Су'</correctAnswer>
  </question>
  <question>
    <id>27</id>
    <image>'1'</image>
    <questionName>'Какую пещеру поначалу также называли «Афганка»'</questionName>
    <answerChoice>
      <list>
        <item>'Мраморную'</item>
        <item>'Эмине-Баир-Хосар'</item>
        <item>'Киик-коба'</item>
        <item>'Бузлук'</item>
      </list>
    </answerChoice>
    <correctAnswer>'Мраморную'</correctAnswer>
  </question>
  <question>
    <id>28</id>
    <image>'1'</image>
    <questionName>'Крымскотатарское название селения Песчаное'</questionName>
    <answerChoice>
      <list>
        <item>'Къапсихор'</item>
        <item>'Аджы Болат'</item>
        <item>'Алма Тамакъ'</item>
        <item>'Эски-Орда'</item>
      </list>
    </answerChoice>
    <correctAnswer>'Алма Тамакъ'</correctAnswer>
  </question>
  <question>
    <id>29</id>
    <image>'1'</image>
    <questionName>'Историческое название селения Орловка'</questionName>
    <answerChoice>
      <list>
        <item>'Мамашай'</item>
        <item>'Аджы Болат'</item>
        <item>'Алма Тамакъ'</item>
        <item>'Эски-Орда'</item>
      </list>
    </answerChoice>
    <correctAnswer>'Мамашай'</correctAnswer>
  </question>
  <question>
    <id>30</id>
    <image>'1'</image>
    <questionName>'Где располагается Азиз Малик-Аштера: большое кладбище, центром которого считалась символическая могила Малика Аштера эн-Нахаи (618—657), сподвижника и военачальника халифа Али?'</questionName>
    <answerChoice>
      <list>
        <item>'Эски-Юрт'</item>
        <item>'Салачыкъ'</item>
        <item>'Эски-Къырым'</item>
        <item>'Кезлев'</item>
      </list>
    </answerChoice>
    <correctAnswer>'Эски-Юрт'</correctAnswer>
  </question>
  <question>
    <id>31</id>
    <image>'1'</image>
    <questionName>'Какой исторический памятник изображен на фото?'</questionName>
    <answerChoice>
      <list>
        <item>'Ханский дворец Девлет-Сарай'</item>
        <item>'Зынджырлы медресе в Салачике'</item>
        <item>'Еникале в Керчи'</item>
        <item>'Мавзолей Джанике-ханым на Чуфут-кале'</item>
      </list>
    </answerChoice>
    <correctAnswer>'Зынджырлы медресе в Салачике'</correctAnswer>
  </question>
  <question>
    <id>32</id>
    <image>'1'</image>
    <questionName>'Какой исторический памятник изображен на фото?'</questionName>
    <answerChoice>
      <list>
        <item>'Ханский дворец Девлет-Сарай'</item>
        <item>'Зынджырлы медресе в Салачике'</item>
        <item>'Мечеть Джума-Джами в Евпатории'</item>
        <item>'Мечеть Узбек-хана в Старом Крыму'</item>
      </list>
    </answerChoice>
    <correctAnswer>'Мечеть Узбек-хана в Старом Крыму'</correctAnswer>
  </question>
  <question>
    <id>33</id>
    <image>'1'</image>
    <questionName>'Крымскотатарское название города Евпатория'</questionName>
    <answerChoice>
      <list>
        <item>'Кезлев'</item>
        <item>'Эски Къырым'</item>
        <item>'Акъмесджит'</item>
        <item>'Кефе'</item>
      </list>
    </answerChoice>
    <correctAnswer>'Кезлев'</correctAnswer>
  </question>
  <question>
    <id>34</id>
    <image>'1'</image>
    <questionName>'Историческое название селения Скалистое'</questionName>
    <answerChoice>
      <list>
        <item>'Мамашай'</item>
        <item>'Аджы Болат'</item>
        <item>'Алма Тамакъ'</item>
        <item>'Тав Бадракъ'</item>
      </list>
    </answerChoice>
    <correctAnswer>'Тав Бадракъ'</correctAnswer>
  </question>
  <question>
    <id>35</id>
    <image>'1'</image>
    <questionName>'Крымскотатарские название селения Староселье'</questionName>
    <answerChoice>
      <list>
        <item>'Мамашай'</item>
        <item>'Салачыкъ'</item>
        <item>'Алма Тамакъ'</item>
        <item>'Тав Бадракъ'</item>
      </list>
    </answerChoice>
    <correctAnswer>'Салачыкъ'</correctAnswer>
  </question>
  <question>
    <id>36</id>
    <image>'1'</image>
    <questionName>'Узкая и длинная коса в северо-восточной части полуострова состоящая в основном из ракушечного материала, отделяющая залив Сиваш от Азовского моря'</questionName>
    <answerChoice>
      <list>
        <item>'Сивашская стрелка'</item>
        <item>'Арабатская стрелка'</item>
        <item>'Ак-Монайская стрелка'</item>
        <item>'Каркинитская стрелка'</item>
      </list>
    </answerChoice>
    <correctAnswer>'Арабатская стрелка'</correctAnswer>
  </question>
  <question>
    <id>37</id>
    <image>'1'</image>
    <questionName>'Крайняя южная точка Крыма'</questionName>
    <answerChoice>
      <list>
        <item>'Мыс Сарыч'</item>
        <item>'Мыс Меганом'</item>
        <item>'Мыс Тарханкут'</item>
        <item>'Мыс Фенер'</item>
      </list>
    </answerChoice>
    <correctAnswer>'Мыс Сарыч'</correctAnswer>
  </question>
  <question>
    <id>38</id>
    <image>'1'</image>
    <questionName>'Крайняя западная точка Крыма'</questionName>
    <answerChoice>
      <list>
        <item>'Мыс Сарыч'</item>
        <item>'Мыс Кара-Мрун'</item>
        <item>'Мыс Тарханкут'</item>
        <item>'Мыс Фенер'</item>
      </list>
    </answerChoice>
    <correctAnswer>'Мыс Кара-Мрун'</correctAnswer>
  </question>
  <question>
    <id>39</id>
    <image>'1'</image>
    <questionName>'Крайняя восточная точка Крыма'</questionName>
    <answerChoice>
      <list>
        <item>'Мыс Сарыч'</item>
        <item>'Мыс Меганом'</item>
        <item>'Мыс Тарханкут'</item>
        <item>'Мыс Фенер'</item>
      </list>
    </answerChoice>
    <correctAnswer>'Мыс Фенер'</correctAnswer>
  </question>
  <question>
    <id>40</id>
    <image>'1'</image>
    <questionName>'Крайняя северная точка Крыма'</questionName>
    <answerChoice>
      <list>
        <item>'Чонгар'</item>
        <item>'Сивашский перешеек'</item>
        <item>'Перекопский перешеек'</item>
        <item>'Армянск'</item>
      </list>
    </answerChoice>
    <correctAnswer>'Перекопский перешеек'</correctAnswer>
  </question>
  <question>
    <id>41</id>
    <image>'1'</image>
    <questionName>'Крымскотатарское название селения Подгородгое
'</questionName>
    <answerChoice>
      <list>
        <item>'Эски-Юрт'</item>
        <item>'Салачыкъ'</item>
        <item>'Алма Тамакъ'</item>
        <item>'Тав Бадракъ'</item>
      </list>
    </answerChoice>
    <correctAnswer>'Эски-Юрт'</correctAnswer>
  </question>
  <question>
    <id>42</id>
    <image>'1'</image>
    <questionName>'Место расположения Зынджырлы Медресе'</questionName>
    <answerChoice>
      <list>
        <item>'Кезлев'</item>
        <item>'Эски-Юрт'</item>
        <item>'Салачыкъ'</item>
        <item>'Эски Къырым'</item>
      </list>
    </answerChoice>
    <correctAnswer>'Салачыкъ'</correctAnswer>
  </question>
  <question>
    <id>43</id>
    <image>'1'</image>
    <questionName>'Крымскотатарское название Перекопского перешейка'</questionName>
    <answerChoice>
      <list>
        <item>'Орта бойну'</item>
        <item>'Ор къапы'</item>
        <item>'Ор бойну'</item>
        <item>'Орта къапы'</item>
      </list>
    </answerChoice>
    <correctAnswer>'Ор бойну'</correctAnswer>
  </question>
  <question>
    <id>44</id>
    <image>'1'</image>
    <questionName>'Историческое название селения Оползневое'</questionName>
    <answerChoice>
      <list>
        <item>'Мамашай'</item>
        <item>'Кикинеиз'</item>
        <item>'Алма Тамакъ'</item>
        <item>'Тав Бадракъ'</item>
      </list>
    </answerChoice>
    <correctAnswer>'Кикинеиз'</correctAnswer>
  </question>
  <question>
    <id>45</id>
    <image>'1'</image>
    <questionName>'Название города Севастополь с греческого означает'</questionName>
    <answerChoice>
      <list>
        <item>'«высокочтимый, священный город» '</item>
        <item>'«город королей»'</item>
        <item>'«город-бухта»'</item>
        <item>'«славный город-герой»'</item>
      </list>
    </answerChoice>
    <correctAnswer>'«высокочтимый, священный город» '</correctAnswer>
  </question>
  <question>
    <id>46</id>
    <image>'1'</image>
    <questionName>'На месте крымскотатарского села Ахтиар (Ак-Яр), как крепость с адмиралтейством, был основан нынешний город'</questionName>
    <answerChoice>
      <list>
        <item>'Феодосия'</item>
        <item>'Керчь'</item>
        <item>'Ялта'</item>
        <item>'Севастополь'</item>
      </list>
    </answerChoice>
    <correctAnswer>'Севастополь'</correctAnswer>
  </question>
  <question>
    <id>47</id>
    <image>'1'</image>
    <questionName>'Территория какого города отображена на фрагменте карты?'</questionName>
    <answerChoice>
      <list>
        <item>'Феодосия'</item>
        <item>'Керчь'</item>
        <item>'Ялта'</item>
        <item>'Севастополь'</item>
      </list>
    </answerChoice>
    <correctAnswer>'Ялта'</correctAnswer>
  </question>
  <question>
    <id>48</id>
    <image>'1'</image>
    <questionName>'Крымскотатарское название памятника архитектуры и истории, расположенного на отвесной 40-метровой Аврориной скале мыса Ай-Тодор в посёлке Гаспра на южном берегу Крыма'</questionName>
    <answerChoice>
      <list>
        <item>'Енъи Къале'</item>
        <item>'Дюльбер сарайы'</item>
        <item>'Кичкине сарайы'</item>
        <item>'Къарылгъач ювасы'</item>
      </list>
    </answerChoice>
    <correctAnswer>'Къарылгъач ювасы'</correctAnswer>
  </question>
  <question>
    <id>49</id>
    <image>'1'</image>
    <questionName>'Название какого города по одной из версий происходит из крымскотатарского языка, на котором дословно означает «рыбная погода»?'</questionName>
    <answerChoice>
      <list>
        <item>'Феодосия'</item>
        <item>'Балаклава'</item>
        <item>'Севастополь'</item>
        <item>'Ялта'</item>
      </list>
    </answerChoice>
    <correctAnswer>'Балаклава'</correctAnswer>
  </question>
  <question>
    <id>50</id>
    <image>'1'</image>
    <questionName>'В 1475г. Каламиту захватили турки и переименовали в «Инкерман», что переводится как'</questionName>
    <answerChoice>
      <list>
        <item>'«пещерная крепость»'</item>
        <item>'«пещерный город»'</item>
        <item>'«город-бухта»'</item>
        <item>'«скрытая пещера»'</item>
      </list>
    </answerChoice>
    <correctAnswer>'«пещерная крепость»'</correctAnswer>
  </question>
  <question>
    <id>51</id>
    <image>'1'</image>
    <questionName>'Крымскотатарское название селения Черноморское'</questionName>
    <answerChoice>
      <list>
        <item>'Мамашай'</item>
        <item>'Кикинеиз'</item>
        <item>'Алма Тамакъ'</item>
        <item>'Акъмечит'</item>
      </list>
    </answerChoice>
    <correctAnswer>'Акъмечит'</correctAnswer>
  </question>
  <question>
    <id>52</id>
    <image>'1'</image>
    <questionName>'Территория какого города отображена на фрагменте карты?'</questionName>
    <answerChoice>
      <list>
        <item>'Феодосия'</item>
        <item>'Алушта'</item>
        <item>'Ялта'</item>
        <item>'Севастополь'</item>
      </list>
    </answerChoice>
    <correctAnswer>'Алушта'</correctAnswer>
  </question>
  <question>
    <id>53</id>
    <image>'1'</image>
    <questionName>'Историческое название селения Межводное'</questionName>
    <answerChoice>
      <list>
        <item>'Ярылгъач'</item>
        <item>'Кикинеиз'</item>
        <item>'Алма Тамакъ'</item>
        <item>'Акъмечит'</item>
      </list>
    </answerChoice>
    <correctAnswer>'Ярылгъач'</correctAnswer>
  </question>
  <question>
    <id>54</id>
    <image>'1'</image>
    <questionName>'Какое самое глубокое озеро в Крыму и крупнейшее озеро Черноморского района?'</questionName>
    <answerChoice>
      <list>
        <item>'Донъузлав'</item>
        <item>'Джарылгъач'</item>
        <item>'Ярылгъач'</item>
        <item>'Пан голю'</item>
      </list>
    </answerChoice>
    <correctAnswer>'Донъузлав'</correctAnswer>
  </question>
  <question>
    <id>55</id>
    <image>'1'</image>
    <questionName>'Название какого озера в переводе с крымскотатарского языка означает «расколовшийся», «треснувший»?'</questionName>
    <answerChoice>
      <list>
        <item>'Донъузлав'</item>
        <item>'Джарылгъач'</item>
        <item>'Ярылгъач'</item>
        <item>'Пан голю'</item>
      </list>
    </answerChoice>
    <correctAnswer>'Джарылгъач'</correctAnswer>
  </question>
  <question>
    <id>56</id>
    <image>'1'</image>
    <questionName>'Какой вариант является одной из гипотез возникновения названия «Къара дениз»?
'</questionName>
    <answerChoice>
      <list>
        <item>'«цветовое» обозначение сторон света, где «чёрный» обозначал север'</item>
        <item>'название дали турки, так как из-за сильной бури их корабли не могли переплыть море'</item>
        <item>'из-за сильных штормов, в которых потонуло множество кораблей'</item>
        <item>'Название морю дали древние греки из-за его свечения в ночи'</item>
      </list>
    </answerChoice>
    <correctAnswer>
    </correctAnswer>
  </question>
  <question>
    <id>57</id>
    <image>'1'</image>
    <questionName>'Крымскотатарское название мыса Прибойный
'</questionName>
    <answerChoice>
      <list>
        <item>'Джангуль'</item>
        <item>'Донузлав'</item>
        <item>'Тарханкут'</item>
        <item>'Карамрун'</item>
      </list>
    </answerChoice>
    <correctAnswer>'Карамрун'</correctAnswer>
  </question>
  <question>
    <id>58</id>
    <image>'1'</image>
    <questionName>'Что означает название Тарханкутского полуострова (Тархан Къут ярымадасы)'</questionName>
    <answerChoice>
      <list>
        <item>'В честь известного золотоордынского правителя Тар-Хана'</item>
        <item>'Тархан — территория, место, освобождённое от налогов'</item>
        <item>'В честь иранского халифа Тархана'</item>
        <item>'Тархан – в переводе с греческого «полуостров»'</item>
      </list>
    </answerChoice>
    <correctAnswer>'Тархан — территория, место, освобождённое от налогов'</correctAnswer>
  </question>
  <question>
    <id>59</id>
    <image>'1'</image>
    <questionName>'Какой прибрежный город изображен на фото?
'</questionName>
    <answerChoice>
      <list>
        <item>'Ялта'</item>
        <item>'Судак'</item>
        <item>'Керчь'</item>
        <item>'Феодосия'</item>
      </list>
    </answerChoice>
    <correctAnswer>'Феодосия'</correctAnswer>
  </question>
  <question>
    <id>60</id>
    <image>'1'</image>
    <questionName>'В переводе с крымскотатарского «Кефе корьфези» это'</questionName>
    <answerChoice>
      <list>
        <item>'Феодосийский маяк'</item>
        <item>'Феодосийский залив'</item>
        <item>'Керченский пролив'</item>
        <item>'Каламитский залив'</item>
      </list>
    </answerChoice>
    <correctAnswer>'Феодосийский залив'</correctAnswer>
  </question>
  <question>
    <id>61</id>
    <image>'1'</image>
    <questionName>'Крымскотатарское название города Белогорск'</questionName>
    <answerChoice>
      <list>
        <item>'Акъмесджит'</item>
        <item>'Кезлев'</item>
        <item>'Кефе'</item>
        <item>'Къарасувбазар'</item>
      </list>
    </answerChoice>
    <correctAnswer>'Къарасувбазар'</correctAnswer>
  </question>
  <question>
    <id>62</id>
    <image>'1'</image>
    <questionName>'Под каким номером на карте отмечен город Къарасувбазар?'</questionName>
    <answerChoice>
      <list>
        <item>'1'</item>
        <item>'2'</item>
        <item>'3'</item>
        <item>'4'</item>
      </list>
    </answerChoice>
    <correctAnswer>'4'</correctAnswer>
  </question>
  <question>
    <id>63</id>
    <image>'1'</image>
    <questionName>'Какой прибрежный город изображен на фото?'</questionName>
    <answerChoice>
      <list>
        <item>'Ялта'</item>
        <item>'Судак'</item>
        <item>'Керчь'</item>
        <item>'Феодосия'</item>
      </list>
    </answerChoice>
    <correctAnswer>'Ялта'</correctAnswer>
  </question>
  <question>
    <id>64</id>
    <image>'1'</image>
    <questionName>'Историческое название города — Карасубазар в переводе с крымскотатарского означает'</questionName>
    <answerChoice>
      <list>
        <item>'«рынок на Карасу»'</item>
        <item>'«Черный замок»'</item>
        <item>'«черная вода»'</item>
        <item>'«рынок черной воды»'</item>
      </list>
    </answerChoice>
    <correctAnswer>'«рынок на Карасу»'</correctAnswer>
  </question>
  <question>
    <id>65</id>
    <image>'1'</image>
    <questionName>'Под каким номером на карте отмечен город Кефе?'</questionName>
    <answerChoice>
      <list>
        <item>'1'</item>
        <item>'2'</item>
        <item>'3'</item>
        <item>'4'</item>
      </list>
    </answerChoice>
    <correctAnswer>'1'</correctAnswer>
  </question>
  <question>
    <id>66</id>
    <image>'1'</image>
    <questionName>'Крымскотатарское название селения Давыдово'</questionName>
    <answerChoice>
      <list>
        <item>'Ярылгъач'</item>
        <item>'Кикинеиз'</item>
        <item>'Шейхкой'</item>
        <item>'Акъмечит'</item>
      </list>
    </answerChoice>
    <correctAnswer>'Шейхкой'</correctAnswer>
  </question>
  <question>
    <id>67</id>
    <image>'1'</image>
    <questionName>'На степном диалекте крымскотатарского языка название города Джанкой означает'</questionName>
    <answerChoice>
      <list>
        <item>'«милая деревня»'</item>
        <item>'«душа-деревня»'</item>
        <item>'«дорогая деревня»'</item>
        <item>'«новая деревня»'</item>
      </list>
    </answerChoice>
    <correctAnswer>'«новая деревня»'</correctAnswer>
  </question>
  <question>
    <id>68</id>
    <image>'1'</image>
    <questionName>'Под каким номером на карте отмечен город Кезлев?'</questionName>
    <answerChoice>
      <list>
        <item>'1'</item>
        <item>'2'</item>
        <item>'3'</item>
        <item>'4'</item>
      </list>
    </answerChoice>
    <correctAnswer>'2'</correctAnswer>
  </question>
  <question>
    <id>69</id>
    <image>'1'</image>
    <questionName>'Под каким номером на карте отмечен город Ор-Къапы?'</questionName>
    <answerChoice>
      <list>
        <item>'1'</item>
        <item>'2'</item>
        <item>'3'</item>
        <item>'4'</item>
      </list>
    </answerChoice>
    <correctAnswer>'3'</correctAnswer>
  </question>
  <question>
    <id>70</id>
    <image>'1'</image>
    <questionName>'Крымскотатарское название селения Азовское'</questionName>
    <answerChoice>
      <list>
        <item>'Ярылгъач'</item>
        <item>'Къалай'</item>
        <item>'Шейхкой'</item>
        <item>'Акъмечит'</item>
      </list>
    </answerChoice>
    <correctAnswer>'Къалай'</correctAnswer>
  </question>
  <question>
    <id>71</id>
    <image>'1'</image>
    <questionName>'Какой прибрежный город изображен на фото?'</questionName>
    <answerChoice>
      <list>
        <item>'Ялта'</item>
        <item>'Судак'</item>
        <item>'Севастополь'</item>
        <item>'Феодосия'</item>
      </list>
    </answerChoice>
    <correctAnswer>'Севастополь'</correctAnswer>
  </question>
  <question>
    <id>72</id>
    <image>'1'</image>
    <questionName>'Какой исторический памятник изображен на фото?'</questionName>
    <answerChoice>
      <list>
        <item>'Ханский дворец Девлет-Сарай'</item>
        <item>'Зынджырлы медресе в Салачике'</item>
        <item>'Еникале в Керчи'</item>
        <item>'Джума Джами в Кезлеве'</item>
      </list>
    </answerChoice>
    <correctAnswer>'Джума Джами в Кезлеве'</correctAnswer>
  </question>
  <question>
    <id>73</id>
    <image>'1'</image>
    <questionName>'Название какого города по одной из версий в переводе с тюркского дословно означает «вода и нагорный лес»?'</questionName>
    <answerChoice>
      <list>
        <item>'Феодосия'</item>
        <item>'Балаклава'</item>
        <item>'Судак'</item>
        <item>'Ялта'</item>
      </list>
    </answerChoice>
    <correctAnswer>'Судак'</correctAnswer>
  </question>
  <question>
    <id>74</id>
    <image>'1'</image>
    <questionName>'Какую гору в средние века греки называли «Фуна»?'</questionName>
    <answerChoice>
      <list>
        <item>'Ай-Петри'</item>
        <item>'Роман-Кош'</item>
        <item>'Демирджи'</item>
        <item>'Чатыр-даг'</item>
      </list>
    </answerChoice>
    <correctAnswer>'Демирджи'</correctAnswer>
  </question>
  <question>
    <id>75</id>
    <image>'1'</image>
    <questionName>'Какой прибрежный город изображен на фото?'</questionName>
    <answerChoice>
      <list>
        <item>'Ялта'</item>
        <item>'Судак '</item>
        <item>'Севастополь'</item>
        <item>'Феодосия'</item>
      </list>
    </answerChoice>
    <correctAnswer>'Судак '</correctAnswer>
  </question>
  <question>
    <id>76</id>
    <image>'1'</image>
    <questionName>'Как переводится с крымскотатарского название горного массива «Демирджи»?'</questionName>
    <answerChoice>
      <list>
        <item>'Наковальня'</item>
        <item>'Мастерская'</item>
        <item>'Кузнец'</item>
        <item>'Мастер'</item>
      </list>
    </answerChoice>
    <correctAnswer>'Кузнец'</correctAnswer>
  </question>
  <question>
    <id>77</id>
    <image>'1'</image>
    <questionName>'Под каким номером «Каламита корьфези»?'</questionName>
    <answerChoice>
      <list>
        <item>'1'</item>
        <item>'2'</item>
        <item>'3'</item>
        <item>'4'</item>
      </list>
    </answerChoice>
    <correctAnswer>'1'</correctAnswer>
  </question>
  <question>
    <id>78</id>
    <image>'1'</image>
    <questionName>'Крымскотатарское название селения Лучистое'</questionName>
    <answerChoice>
      <list>
        <item>'Ярылгъач'</item>
        <item>'Къалай'</item>
        <item>'Шейхкой'</item>
        <item>'Демирджи'</item>
      </list>
    </answerChoice>
    <correctAnswer>'Демирджи'</correctAnswer>
  </question>
  <question>
    <id>79</id>
    <image>'1'</image>
    <questionName>'Под каким номером «Джарылгъач корьфези»?'</questionName>
    <answerChoice>
      <list>
        <item>'1'</item>
        <item>'2'</item>
        <item>'3'</item>
        <item>'4'</item>
      </list>
    </answerChoice>
    <correctAnswer>'3'</correctAnswer>
  </question>
  <question>
    <id>80</id>
    <image>'1'</image>
    <questionName>'Крымскотатарское название селения Солнечногорское'</questionName>
    <answerChoice>
      <list>
        <item>'Ярылгъач'</item>
        <item>'Къуру Озен'</item>
        <item>'Шейхкой'</item>
        <item>'Демирджи'</item>
      </list>
    </answerChoice>
    <correctAnswer>'Къуру Озен'</correctAnswer>
  </question>
  <question>
    <id>81</id>
    <image>'1'</image>
    <questionName>'Под каким номером «Кефе корьфези»?'</questionName>
    <answerChoice>
      <list>
        <item>'1'</item>
        <item>'2'</item>
        <item>'3'</item>
        <item>'4'</item>
      </list>
    </answerChoice>
    <correctAnswer>'2'</correctAnswer>
  </question>
  <question>
    <id>82</id>
    <image>'1'</image>
    <questionName>'Крымскотатарское название селения Орлиное'</questionName>
    <answerChoice>
      <list>
        <item>'Ярылгъач'</item>
        <item>'Къуру Озен'</item>
        <item>'Байдар'</item>
        <item>'Демирджи'</item>
      </list>
    </answerChoice>
    <correctAnswer>'Байдар'</correctAnswer>
  </question>
  <question>
    <id>83</id>
    <image>'1'</image>
    <questionName>'Крымскотатарское название селения Кировское'</questionName>
    <answerChoice>
      <list>
        <item>'Ислям Терек'</item>
        <item>'Къуру Озен'</item>
        <item>'Шейхкой'</item>
        <item>'Демирджи'</item>
      </list>
    </answerChoice>
    <correctAnswer>'Демирджи'</correctAnswer>
  </question>
  <question>
    <id>84</id>
    <image>'1'</image>
    <questionName>'Под каким номером «Арабат бели»?'</questionName>
    <answerChoice>
      <list>
        <item>'1'</item>
        <item>'2'</item>
        <item>'3'</item>
        <item>'4'</item>
      </list>
    </answerChoice>
    <correctAnswer>'4'</correctAnswer>
  </question>
  <question>
    <id>85</id>
    <image>''</image>
    <questionName>'Историческое название села Соколиное, что в переводе означает "голубой глаз"'</questionName>
    <answerChoice>
      <list>
        <item>'Коккозь'</item>
        <item>'Коклуз'</item>
        <item>'Мавыкозь'</item>
        <item>'Ешильозен'</item>
      </list>
    </answerChoice>
    <correctAnswer>'Коккозь'</correctAnswer>
  </question>
  <question>
    <id>86</id>
    <image>''</image>
    <questionName>'На какой реке находится водопад "Серебряные струи", что в ущелье "Малого каньона" (фото до катастрофы 2016 года)'</questionName>
    <answerChoice>
      <list>
        <item>'Коккозь'</item>
        <item>'Сары-Узень'</item>
        <item>'Кок-Узень'</item>
        <item>'Улу-Узень'</item>
      </list>
    </answerChoice>
    <correctAnswer>'Сары-Узень'</correctAnswer>
  </question>
  <question>
    <id>87</id>
    <image>''</image>
    <questionName>'Мечеть, построенная по иницииативе князя Феликса Юсупова в Соколином, называется'</questionName>
    <answerChoice>
      <list>
        <item>'Хан Джами'</item>
        <item>'Юсуф Джами'</item>
        <item>'Коккозь Джами'</item>
        <item>'Кок Джами'</item>
      </list>
    </answerChoice>
    <correctAnswer>'Коккозь Джами'</correctAnswer>
  </question>
  <question>
    <id>88</id>
    <image>''</image>
    <questionName>'Какой знаменательный географический объект находится в окресностях села Соколиное, Бахчисарайского района'</questionName>
    <answerChoice>
      <list>
        <item>'Большой каньон Крыма'</item>
        <item>'Гора Демирджи'</item>
        <item>'Река Улу-Узень'</item>
        <item>'Гора Роман-Кош'</item>
      </list>
    </answerChoice>
    <correctAnswer>'Большой каньон Крыма'</correctAnswer>
  </question>
  <question>
    <id>89</id>
    <image>''</image>
    <questionName>'Назовите гору, высота которой 1234м, через которую проходит трасса Ялта-Бахчисарай'</questionName>
    <answerChoice>
      <list>
        <item>'Роман-Кош'</item>
        <item>'Ай-Петри'</item>
        <item>'Карадаг'</item>
        <item>'Чатырдаг'</item>
      </list>
    </answerChoice>
    <correctAnswer>'Ай-Петри'</correctAnswer>
  </question>
  <question>
    <id>90</id>
    <image>''</image>
    <questionName>'Из какого языка исходит название горы Ай-Петри'</questionName>
    <answerChoice>
      <list>
        <item>'Крымскотатарского'</item>
        <item>'Турецкого'</item>
        <item>'Греческого'</item>
        <item>'Итальянского'</item>
      </list>
    </answerChoice>
    <correctAnswer>'Греческого'</correctAnswer>
  </question>
  <question>
    <id>91</id>
    <image>''</image>
    <questionName>'Плато какой горы является популярным туристическим объектом близ Ангарского перевала'</questionName>
    <answerChoice>
      <list>
        <item>'Чатыр-Даг'</item>
        <item>'Демерджи'</item>
        <item>'Аю-Даг'</item>
        <item>'Парагильмен'</item>
      </list>
    </answerChoice>
    <correctAnswer>'Чатыр-Даг'</correctAnswer>
  </question>
</list>
